Metadata-Version: 2.1
Name: vk-api-for-groups
Version: 0.0.1
Summary: A package that provides simple vk-api integration. Mostly for groups-related methods.
Home-page: https://github.com/Rokoel/api_for_groups_vk
Author: Rokoel
Author-email: rokoelvel@gmail.com
License: MIT Licence
Project-URL: Bug Tracker, https://github.com/Rokoel/api_for_groups_vk/issues
Platform: UNKNOWN
Classifier: License :: OSI Approved :: MIT License
Classifier: Operating System :: OS Independent
Classifier: Programming Language :: Python :: 3
Requires-Python: >=3.8
License-File: LICENSE.txt
